aiomigrator/__init__.py
aiomigrator/commands.py
aiomigrator/main.py
aiomigrator/queries.py
aiomigrator/templates.py
aiomigrator-0.1.0.dist-info/LICENSE
aiomigrator-0.1.0.dist-info/METADATA
aiomigrator-0.1.0.dist-info/WHEEL
aiomigrator-0.1.0.dist-info/top_level.txt
aiomigrator-0.1.0.dist-info/RECORD
