Metadata-Version: 2.1
Name: aiomigrator
Version: 0.1.0
Summary: Simple tool for aiopg migrations
Author-email: Dmytro Malikin <dmytro.malikin@gmail.com>
License: MIT License
Project-URL: Homepage, https://github.com/dmalikin/aiomigrator
Project-URL: Bug Tracker, https://github.com/dmalikin/aiomigrator/issues
Classifier: Programming Language :: Python :: 3
Classifier: License :: OSI Approved :: MIT License
Classifier: Operating System :: OS Independent
Requires-Python: >=3.8
License-File: LICENSE
